{
  "Moon": {
    "meta": {
      "lead": "Куда направить фокус на этой неделе"
    },
    "houses": {
      "1": {
        "theme": "",
        "items": [
          "Любая физическая активность, спорт",
          "Время для себя, посещение салонов красоты",
          "Изменение имиджа, стиля одежды, разбор гардероба"
        ]
      },
      "2": {
        "theme": "",
        "items": [
          "Любые финансовые операции",
          "Закупка любого товара, пополнение запасов",
          "Работа со стилистом, покупка одежды",
          "Восстановление ресурса: вкусная еда, массаж"
        ]
      },
      "3": {
        "theme": "",
        "items": [
          "Работа с информацией: поиск, курсы/обучение, чтение, ведение блога, создание контента, проведение эфиров, лекций",
          "Оформление любых документов, обращение в структуры за справками",
          "Активное общение, переписка, обмен информацией",
          "Короткие поездки, командировки, велосипедные и пешие прогулки"
        ]
      },
      "4": {
        "theme": "",
        "items": [
          "Посещение родных мест, родственников, родителей",
          "Уборка пространства (от рабочего стола и чистки смартфона до уборки дома и мойки автомобиля)",
          "Любые действия с недвижимостью и землей: ремонт, перестановка",
          "Спокойный отдых и расслабление: баня, СПА, хамам"
        ]
      },
      "5": {
        "theme": "",
        "items": [
          "Запуск продаж, презентации продуктов/проектов",
          "Новые направления в бизнесе, старт новых проектов",
          "Творчество, хобби",
          "Досуг с детьми (игры, походы, мероприятия)",
          "Активный отдых, развлечения и шоппинг"
        ]
      },
      "6": {
        "theme": "",
        "items": [
          "Уборка пространства, оплата счетов и бытовые дела",
          "Запись к врачу, анализы, лечение, начало приема БАДов, витаминов",
          "Уход, забота о близких и их здоровье",
          "Покупка домашних питомцев, уход за ними, груминг",
          "Найм сотрудников, обслуживающего персонала, вызов клинига, мастеров по ремонту"
        ]
      },
      "7": {
        "theme": "",
        "items": [
          "Переговоры, заключение компромиссов, деловые встречи, подписание договоров, совместные проекты",
          "Проведение консультаций / обращение за консультациями к специалистам",
          "Встречи с друзьями, девичники",
          "Романтические свидания, культурный отдых с близкими людьми (театр, выставка)"
        ]
      },
      "8": {
        "theme": "",
        "items": [
          "Любые банковские операции, инвестирование, ипотека, взятие/погашение кредитов и займов",
          "Решение вопросов наследства, налогов, оформление страховок",
          "Консультации с психологом/коучем",
          "Любые энергетические и магические практики, восполнение энергии, отпускание отжившего, денежные медитации"
        ]
      },
      "9": {
        "theme": "",
        "items": [
          "Планирование поездок, путешествий, покупки билетов и бронирования отелей, начало длительных/заграничных поездок",
          "Старт нового длительного обучения, общение с экспертами, учителями, гуру, работа с наставником, ментором",
          "Время для решения юридических вопросов",
          "Посещение престижных мероприятий"
        ]
      },
      "10": {
        "theme": "",
        "items": [
          "Решение всех вопросов, связанных с законом, властью, чиновниками",
          "Беседы с начальниками и вышестоящими людьми",
          "Оплата кредитов и долговых обязательств",
          "Решение важных рабочих задач, переходов на новую должность, обретения нового статуса"
        ]
      },
      "11": {
        "theme": "",
        "items": [
          "Старт новых проектов в онлайне и социальных сетях, внедрение новых технологий",
          "Общение и встречи с единомышленниками, коллегами, подписчиками, мозговые штурмы, планерки, вступление в сообщества",
          "Консультации с астрологом и нумерологом, долгосрочное планирование, прогнозирование",
          "Покупка или ремонт техники"
        ]
      },
      "12": {
        "theme": "",
        "items": [
          "Уединение, ретриты, медитация, восстановление, слияние с природой",
          "Любые эзотерические практики, карта желаний, визуализация, взятие аскез, работа с подсознанием, интуицией, снами",
          "Посещение храмов, поездок по святым местам и местам силы",
          "Плановая госпитализация",
          "Благотворительность"
        ]
      }
    }
  },
  "Sun": {
    "meta": {
      "lead": "Приоритетные сферы месяца"
    },
    "houses": {
      "1": {
        "theme": "Личность, Тело, Новые начинания",
        "items": [
          "Активно проявляйте себя и берите инициативу: начинайте новый проект или то, что давно откладывали, развивайте личный бренд",
          "Занимайтесь своим имиджем: обновляйте прическу, гардероб, покупайте качественные вещи для себя",
          "Занимайтесь развитием и укреплением своего тела: начинайте курс фитнеса, перейдите на новое питание, пройдите чек-ап организма",
          "Отстаивайте свои границы, учитесь говорить «нет», и проявляйте здоровый эгоизм"
        ]
      },
      "2": {
        "theme": "Ресурсы, Финансы, Самоценность",
        "items": [
          "Решайте любые финансовые вопросы: составить бюджет, закрыть мелкие долги, открыть накопительный счет",
          "Повышайте доход: попросите прибавку, найдите подработку, повысьте цены на свои услуги, делайте денежные практики",
          "Инвестируйте в качество: покупайте вещи, которые будут служить долго и приносить удовольствие",
          "Работайте с самооценкой: выписывайте свои достижения и сильные стороны, повышайте внутреннюю ценность"
        ]
      },
      "3": {
        "theme": "Общение, Обучение, Близкое окружение",
        "items": [
          "Активно общайтесь и налаживайте связи с братьями/сестрами, соседями, посещайте местные мероприятия, заводите новые знакомства",
          "Работайте с информацией: проходите курсы, тренинги, марафоны, учитесь вождению, пишите статьи, книгу, активно ведите блог",
          "Больше будьте в движении: совершайте короткие поездки на выходные/командировки. Много ходите пешком, велосипед/ролики",
          "Занимайтесь документами: наведите порядок в архивах, оформляйте страховки, права, визы, заказывайте справки"
        ]
      },
      "4": {
        "theme": "Семья, Недвижимость, Внутренний фундамент",
        "items": [
          "Улучшайте жилище: генеральная уборка, перестановка, ремонт, покупка предметов для интерьера",
          "Занимайтесь вопросами недвижимости: покупка/продажа/аренда, строительство, переезд, оформление документов",
          "Укрепляйте семейные узы: планируйте семейные поездки, проводите больше времени с родителями, детьми и близкими родственниками",
          "Занимайтесь психологией: проработайте детские травмы, найдите ощущение внутренней безопасности и покоя"
        ]
      },
      "5": {
        "theme": "Творчество, Любовь, Радость, Дети",
        "items": [
          "Занимайтесь творчеством: хобби, рисование, танцы, музыка, или любым делом, которое приносит чистую радость",
          "Запускайте и продвигайте свои бизнес-проекты. Совершайте покупки и продажи",
          "Посвящайте время романтике: ходите на свидания, обновляйте отношения с партнером, устраивайте романтические сюрпризы",
          "Отправляйтесь в отпуск с близкими, посещайте театр, концерты, развлечения",
          "Проводите качественное время с детьми. Планируйте беременность"
        ]
      },
      "6": {
        "theme": "Рутина, Работа, Здоровье, Служение",
        "items": [
          "Оптимизируйте рутину: внедряйте полезные привычки, наведите порядок на рабочем столе и в компьютере, решайте бытовые вопросы, нанимайте помощников",
          "Занимайтесь здоровьем: плановые визиты к врачу, переходите на здоровое питание, принимайте витамины, ходите на массаж, в спортзал",
          "Помогайте другим: давайте консультации, помогайте коллегам, заботьтесь о домашних животных",
          "Улучшайте профессиональные навыки: осваивайте новые рабочие инструменты, которые повысят вашу эффективность"
        ]
      },
      "7": {
        "theme": "Партнерства, Брак, Договора",
        "items": [
          "Заключайте союзы: благоприятное время для регистрации брака, начала серьезных отношений, поиска бизнес-партнера. Подписывайте важные документы, контракты, соглашения",
          "Сотрудничайте: в этот период успех приходит через сотрудничество, коллаборации, а не в одиночку",
          "Берите консультации у специалистов, решайте конфликты через компромисс/медиатора/психолога",
          "Проводите больше времени с супругом или любимым человеком, общайтесь с друзьями, выезжайте на отдых или мероприятия"
        ]
      },
      "8": {
        "theme": "Трансформация, Чужие ресурсы, Глубинная психология",
        "items": [
          "Решайте финансовые вопросы: наследство, налоги, оформляйте кредиты, ипотеки, страховки",
          "Отпускайте старое: избавляйтесь от всего что изжило себя (вещи, отношения, убеждения) чтобы впустить новое, берите аскезы",
          "Идите в глубокую терапию, занимайтесь своим внутренним миром: психоанализ, регрессии, работа с теневыми сторонами личности",
          "Обновляйте интимную жизнь: углубляйте эмоциональную и физическую связь с партнером",
          "Планируйте интенсивный период работы именно на эти дни"
        ]
      },
      "9": {
        "theme": "Расширение горизонтов, Путешествия, Высшее знание",
        "items": [
          "Учитесь глобально: высшее образование, изучайте языки/философию/религию, берите наставничество, повышайте квалификацию",
          "Повышайте уровень жизни и внедряйте новые полезные привычки высокой нормы",
          "Путешествуйте: за границу или в места с другой культурой, контактируйте с иностранцами",
          "Участвуйте в крупных проектах: делитесь своим экспертным мнением, своей философией, преподавайте, пишите книги",
          "Решайте юридические вопросы: благоприятное время для судебных процессов, апелляций и решения визовых вопросов"
        ]
      },
      "10": {
        "theme": "Карьера, Статус, Признание",
        "items": [
          "Занимайтесь вопросами карьеры, статуса и продвижения, просите о повышении, обновляйте резюме, меняйте работу на более статусную, берите на себя руководство проектами",
          "Общайтесь с авторитетами: налаживайте связи с начальством, вышестоящими лицами, наставниками и государственными структурами",
          "Ставьте глобальные цели: определите каким вы видите свой профессиональный путь на годы вперед",
          "Решайте вопросы с недвижимостью, занимайтесь делами родителей"
        ]
      },
      "11": {
        "theme": "Друзья, Сообщества, Мечты, Технологии",
        "items": [
          "Ставьте цели на будущее: на 1-3-5 лет, корректируйте свой курс, планируйте долгосрочные проекты, мечтайте в деталях, визуализируйте",
          "Работайте с технологиями: осваивайте новые соцсети для самореализации, создавайте массовые проекты и продукты, продвигайте их в интернете",
          "Расширяйте круг общения: посещайте конференции, вступайте в клубы по интересам, профессиональные сообщества",
          "Вовлекайтесь в волонтерские, социальные, экологические проекты, помогайте друзьям",
          "Следите за модой/политикой/экономикой, новостями"
        ]
      },
      "12": {
        "theme": "Подсознание, Уединение, Завершение циклов",
        "items": [
          "Уединяйтесь и отдыхайте: возьмите передышку, ретрит, проведите время в тишине, на природе, наедине с собой, практикуйте медитации, йогу",
          "Завершайте старые дела: закройте хвосты, разберите старые завалы, простите обиды",
          "Совершайте добрые дела и занимайтесь благотворительностью",
          "Работайте со снами и интуицией, ведите дневник сновидений, прислушивайтесь к внутреннему голосу"
        ]
      }
    }
  },
  "Mercury": {
    "meta": {
      "lead": "Лучшее время для сбора информации, полезных коммуникаций, наведения порядка и ремонта в темах"
    },
    "houses": {
      "1": {
        "theme": "Фокус на Вас, вашем Я, и личных стартапах.",
        "items": [
          "Обучение и сбор информации: Изучение тем самопрезентации, личного брендинга, имиджа, макияжа, а также изучение точной эзотерики: астрологии, нумерологии. Обучение танцам, йоге.",
          "Сбор информации о новых методиках фитнеса, биохакинге или системах питания, подходящих именно вашему типу телосложения.",
          "Чтение книг по саморазвитию, тайм-менеджменту и для ваших личных целей.",
          "Порядок и ремонт: Ревизия личного гардероба: отсортируйте вещи, отдайте ненужное.",
          "Наведение порядка в личных документах (паспорт, права, сертификаты).",
          "Мелкий ремонт личных вещей, обуви, гаджетов, которыми вы пользуетесь ежедневно."
        ]
      },
      "2": {
        "theme": "Фокус на материальной безопасности и денежных потоках",
        "items": [
          "Обучение и сбор информации: Изучайте финансовую грамотность, инвестирование, ведение личного бюджета, а также дизайн.",
          "Сбор информации о новых способах монетизации ваших навыков, налоговых льготах.",
          "Порядок и ремонт: Полный аудит финансов: разбор банковских приложений, отмена ненужных подписок, составление таблицы доходов/расходов.",
          "Наведение порядка в кошельке, ключнице, сейфе.",
          "Ремонт или обслуживание вещей, которые приносят доход (инструменты, рабочая техника, автомобиль и т.д.)."
        ]
      },
      "3": {
        "theme": "Пик ментальной активности, общения, обучения",
        "items": [
          "Обучение и сбор информации: Идеальное время для старта любых курсов, особенно курсов по блогингу, написанию текстов, ораторскому мастерству, изучение иностранных языков.",
          "Сбор информации по широкому кругу вопросов, чтение статей, подкастов, аналитических отчетов.",
          "Порядок и ремонт: Генеральная уборка в телефоне и на компьютере: удаление скриншотов, сортировка файлов, очистка почты. Уборка в салоне машины, автомойка.",
          "Наведение порядка в бумажных документах, блокнотах, органайзерах.",
          "Ремонт автомобиля, а также мелкой бытовой техники, смартфонов, планшетов"
        ]
      },
      "4": {
        "theme": "Фокус на фундаменте, жилище и внутреннем мире",
        "items": [
          "Обучение и сбор информации: Изучение генеалогии, составление семейного древа, сбор семейной истории, родовые практики.",
          "Сбор информации по дизайну интерьера, фэншуй, ландшафтному дизайну, ремонту.",
          "Чтение литературы по детской психологии или глубинной психологии (работа с внутренним ребенком).",
          "Порядок и ремонт: Наводите идеальный порядок дома: разбор шкафов, антресолей, кладовок.",
          "Делайте ремонт дома, или мелкий бытовой ремонт: починка сантехники, мебели, бытовой техники.",
          "Оцифровка и систематизация семейных фотоархивов, порядок в документах на недвижимость."
        ]
      },
      "5": {
        "theme": "Фокус на радости, самовыражении и развлечениях",
        "items": [
          "Обучение и сбор информации: Изучайте любые творческие дисциплины: рисование, музыка, актерское мастерство, танцы.",
          "Обучение по межличностным отношениям, а также детскому развитию, педагогике, игровым методикам.",
          "Изучение основ трейдинга, фондового рынка.",
          "Порядок и ремонт: Наводите порядок в вашем бизнесе, проектах, продуктах или пространстве для хобби.",
          "Ревизия детских вещей, игрушек, книг, подготовка одежды для передачи/продажи.",
          "Планируйте развлечения: составление списков мест для отдыха и развлечений, поиск отелей для отпуска."
        ]
      },
      "6": {
        "theme": "Фокус на алгоритмах и эффективности",
        "items": [
          "Обучение и сбор информации: Изучайте дизайн, новые рабочие программы, софт, нейросети, все что ускорит вашу рутину.",
          "Изучайте всё что связано с темой здоровья: ЗОЖ, нутрициологию, психосоматику, телесную терапию и т.д.",
          "Изучение алгоритмов и пошаговых инструкций ко всему, чем вы пользуетесь.",
          "Порядок и ремонт: Оптимизация рабочего места: эргономика, сортировка рабочих папок, настройка удобных шаблонов.",
          "Ревизия домашней аптечки (проверка сроков годности), косметички, средств для уборки.",
          "Порядок в документах и рационе домашних животных, запись к ветеринару."
        ]
      },
      "7": {
        "theme": "Фокус на партнерстве, браке, договорах",
        "items": [
          "Обучение и сбор информации: Изучайте психологию отношений, как личных, так и деловых, проходите курсы по отношениям.",
          "Работайте над постановкой голоса и речью.",
          "Изучайте договорное право, юридические вопросы, проходите курсы по медиации, переговорам, техникам ненасильственного общения.",
          "Порядок и ремонт: Внимательно вычитывайте и подписывайте важные договоры, контракты, соглашения.",
          "Наводите порядок в совместных с партнером документах, финансах, планировщиках.",
          "Занимайтесь урегулированием судебных или официальных споров, пишите официальные претензии/ответы."
        ]
      },
      "8": {
        "theme": "Фокус на глубинном анализе, скрытых данных, эзотерике",
        "items": [
          "Обучение и сбор информации: Изучайте эзотерику, астрологию, таро, НЛП, психологию теневых сторон личности.",
          "Посещайте бизнес-тренинги, изучайте инвестирование.",
          "Читайте детективы, триллеры, глубокую психологическую или философскую литературу.",
          "Порядок и ремонт: Ревизия кредитов, ипотеки, долгов: составление графика погашения, рефинансирование.",
          "Наводите порядок в страховых полисах, налоговых документах, завещаниях.",
          "Выбрасывайте сломанные, «тяжелые» вещи, генеральная уборка в «слепых» зонах дома (под ванной, за шкафами)."
        ]
      },
      "9": {
        "theme": "Фокус на масштабировании знаний и глобальном планировании",
        "items": [
          "Обучение и сбор информации: Старт фундаментального, длительного обучения",
          "Изучайте личный бренд, философию, религию, иностранную культуру и духовные практики, иностранные языки.",
          "Сбор информации для написания статьи, книги, создания масштабного обучающего продукта.",
          "Порядок и ремонт: Планирование дальних поездок: сбор информации о маршрутах, бронь билетов, оформление виз.",
          "Наведение порядка в домашней библиотеке, систематизация учебных конспектов и лекций. Разбор архивов старых учебных материалов, сертификатов."
        ]
      },
      "10": {
        "theme": "Фокус на профессиональном имидже и социальных лифтах",
        "items": [
          "Обучение и сбор информации: Повышайте квалификацию по вашей прямой профессии, получайте новые сертификации, повышающие ваш статус.",
          "Посещайте бизнес-тренинги, изучайте темы лидерства, управления персоналом, корпоративной этики, PR.",
          "Собирайте информацию о трендах в вашей индустрии, делайте анализ рынка труда.",
          "Порядок и ремонт: Обновляйте резюме, портфолио, деловые фотографии, визитки.",
          "Наведение порядка в деловых контактах, профессиональных чатах.",
          "Планирование карьерной стратегии на год вперед, составление списка достижений."
        ]
      },
      "11": {
        "theme": "Фокус на коллективном взаимодействии, сетях и инновациях",
        "items": [
          "Обучение и сбор информации: Изучайте ведение и оформление блогов, SMM, алгоритмов соцсетей, нейросети, IT-тренды, футурологию, астрологию, нумерологию.",
          "Осваивайте нетворкинг, ораторское мастерство для выступлений перед аудиторией.",
          "Порядок и ремонт: Цифровая уборка в соцсетях: отписка от неактуальных каналов, чистка списков друзей, архивация старых постов, чистка в мессенджерах (удаление старых чатов).",
          "Ремонт или настройка роутера, интернета, смартфона, любой «умной» техники."
        ]
      },
      "12": {
        "theme": "Фокус на внутренней тишине, интуиции и завершении ментальных циклов",
        "items": [
          "Обучение и сбор информации: Изучайте техники медитации, дыхательные практики, Йогу, работу с чакрами, кундалини, рейки, анализ сновидений.",
          "Проходите психологические тренинги, изучайте информацию по арт-терапии, психосоматике, работе с бессознательным.",
          "Читайте художественную литературу, поэзию.",
          "Уходите в информационный детокс.",
          "Порядок и ремонт: Завершение старых дел, подведение ментальных итогов, написание «утренних страниц» для разгрузки головы.",
          "«Цифровая уборка» на жестких дисках и в облачных хранилищах.",
          "Наведение порядка в скрытых местах: антресолях, дальних полках шкафов, багажнике авто."
        ]
      }
    }
  },
  "Venus": {
    "meta": {
      "lead": "Лучшее время для планирования выгодных вложений, свиданий, наполнения ресурсом, получения удовольствия через"
    },
    "houses": {
      "1": {
        "theme": "Внешность, личность, самопрезентация.  Время сиять! Венера здесь делает вас магнетически притягательным.",
        "items": [
          "Финансы и покупки: Активно наращивайте свой доход, ищите дополнительные источники. Время зарабатывать и тратить ресурсы на себя и свои удовольствия. Обновите гардероб, купите парфюм, украшения или аксессуары. Покупки в этот период усилят вашу харизму.",
          "Удовольствия: Запланируйте поход к косметологу, на массаж или в спа. Самое время подобрать идеальный уход.",
          "Личная жизнь: Наслаждайтесь вниманием к своей персоне. Ходите на свидания, если вы в поиске, или устройте романтический вечер для себя и партнера, где вы - в центре внимания."
        ]
      },
      "2": {
        "theme": "Личные финансы, материальные ценности. Период финансового благополучия и материальных удовольствий.",
        "items": [
          "Финансы: Вкладывайте деньги в свои будущие проекты, время безопасных, консервативных инвестиций.",
          "Покупки: Приобретайте дорогие, качественные и статусные вещи, которые будут радовать глаз и служить долго (ювелирные украшения, техника, предметы искусства).",
          "Удовольствия: Позвольте себе гастрономические и телесные удовольствия, купите вкусные и красивые продукты, окружите себя тактильно приятными вещами (шелк, кашемир, мягкие ткани), сходите на массаж."
        ]
      },
      "3": {
        "theme": "Коммуникация, короткая логистика, обучение. Время приятного общения, эстетичных поездок и легких удовольствий.",
        "items": [
          "Финансы и покупки: Приобретайте авто/мото/вело транспортные средства, смартфоны, гаджеты, красивую канцелярию, книги, подписки на онлайн-кинотеатры или музыкальные сервисы. Вкладывайте в свое обучение и курсы.",
          "Удовольствия: Спонтанные красивые поездки на выходные за город или в соседний город. Наведение гармонии в общении с братьями/сестрами или соседями.",
          "Личная жизнь: Флирт, легкие романы, приятные переписки. Идеально для свиданий в кафе, на выставках, в книжных магазинах или на мастер-классах."
        ]
      },
      "4": {
        "theme": "Дом, семья, недвижимость, внутренний комфорт. Время превратить свое жилище в произведение искусства и тихую гавань.",
        "items": [
          "Финансы и покупки: Отличный период для покупки дома, квартиры, земли или просто новой красивой мебели, текстиля, декора.",
          "Удовольствия и личная жизнь: Уютные домашние вечера, прием гостей, семейные ужины при свечах. Гармонизация отношений с родителями и близкими.",
          "Эстетика пространства: Наймите дизайнера для консультации, сделайте косметический ремонт с упором на красоту, переставьте мебель, чтобы энергия в доме текла гармонично."
        ]
      },
      "5": {
        "theme": "Романтика, творчество, дети, развлечения. Самый «вкусный» и романтический транзит Венеры, пик гедонизма.",
        "items": [
          "Финансы и покупки: Траты на отпуск, хобби, развлечения, подарки детям или любимому человеку. Осторожно: Венера здесь может подталкивать к рискованным спекуляциям на бирже — лучше избегать азартных игр и сомнительных вложений.",
          "Удовольствия: Походы в театр, на концерты, вечеринки. Занятия творчеством (танцы, рисование, пение) ради чистого кайфа, а не результата.",
          "Личная жизнь: Время для ярких свиданий, начала новых романов, признаний в любви. Если вы в паре — устройте отпуск вдвоем или верните «конфетно-букетный» период."
        ]
      },
      "6": {
        "theme": "Рутина, здоровье, работа, животные. Время сделать свою повседневность красивой и приятной.",
        "items": [
          "Финансы и покупки: Вкладывайте деньги в свое здоровье, покупка красивой посуды, рабочей формы, рабочих инструментов, растений для офиса. Превращение скучной работы в эстетичный процесс.",
          "Удовольствия: Внедрение приятных бьюти-ритуалов, покупка качественной косметики, запись на приятные оздоровительные процедуры (йога, пилатес, спа). Удовольствие от заботы о домашних питомцах (грумер, покупка красивых аксессуаров, вкусных кормов).",
          "Личная жизнь: Выстраивайте хорошие отношения с коллегами, создание теплой атмосферы в коллективе."
        ]
      },
      "7": {
        "theme": "Брак, партнерства, официальные отношения. Фокус на союзах и договорах.",
        "items": [
          "Финансы и вложения: Подписание выгодных контрактов, создание совместных предприятий, партнерские инвестиции. Удачное время, чтобы брать консультации у экспертов или начинать свою консультационную деятельность. Совершайте покупки вместе с партнером.",
          "Удовольствия: Романтические ужины в ресторанах, совместное посещение светских мероприятий, обучение парным танцам.",
          "Личная жизнь: Отличное время для помолвки, свадьбы, начала серьезных отношений или перехода с партнером на новый уровень близости. Встреча значимого человека."
        ]
      },
      "8": {
        "theme": "Чужие финансы, интимность, трансформация, кризисы. Время глубоких страстей, совместных ресурсов и эстетической трансформации.",
        "items": [
          "Финансы и вложения: Решение вопросов с кредитами, ипотекой, алиментами, налогами. Получение денег от партнера (подарки, совместный бюджет). Инвестиции в чужие проекты или венчур.",
          "Удовольствия: Эстетическая стоматология, татуаж, лазерные процедуры, иглоукалывание.",
          "Личная жизнь: Углубление интимной близости, эксперименты в постели, работа с сексологом для гармонизации отношений."
        ]
      },
      "9": {
        "theme": "Путешествия, философия, высшее образование, культура. Время расширять горизонты через красоту и новые впечатления.",
        "items": [
          "Финансы и покупки: Покупка билетов на курорт, в дальние путешествия, приобретение иностранной одежды, книг на языке оригинала, оплата дорогих обучающих курсов или ретритов, тратить на реализацию давних желаний.",
          "Удовольствия: Поездки в красивые места, туризм, посещение иностранных ресторанов, изучение искусства и культуры других стран.",
          "Личная жизнь: Романы с иностранцами, знакомства в поездках или в университетской среде."
        ]
      },
      "10": {
        "theme": "Карьера, статус, репутация, общество. Время быть любимчиком судьбы и начальства.",
        "items": [
          "Налаживайте близкие контакты с руководством и вышестоящими лицами. Стартуйте новые проекты и запускайте рекламные кампании.",
          "Финансы и вложения: Инвестиции в старт новых проектов, рекламу и свой профессиональный имидж (стилист, дорогой деловой костюм). Покупка статусных аксессуаров (часы, портфель/сумка).",
          "Удовольствия: Посещение светских раутов, премий, выставок. Наслаждение общественным признанием и похвалой.",
          "Личная жизнь и отношения: Гармонизация отношений с руководством, наставниками, вышестоящими людьми. Старт отношений с человеком выше по статусу или возрасту."
        ]
      },
      "11": {
        "theme": "Друзья, соцсети, мечты, клубы по интересам. Время социальных удовольствий, нетворкинга и исполнения желаний.",
        "items": [
          "Финансы и покупки: Вложения в массовые продукты, свои или чужие, - краудфандинг, инвестиции в стартапы или IT-проекты. Покупка вещей для ведения блога, красивого контента в соцсетях, гаджетов.",
          "Удовольствия: Походы на вечеринки, концерты, фестивали, тусовки с друзьями. Посещение эстетичных мест (арт-пространства, модные бары).",
          "Личная жизнь: Знакомства через друзей, в соцсетях или на тематических мероприятиях. Гармонизация отношений в своем круге общения."
        ]
      },
      "12": {
        "theme": "Уединение, подсознание, духовность, скрытые сферы. Время для тихой радости, духовной красоты и тайных удовольствий",
        "items": [
          "Финансы и покупки: Благотворительность, пожертвования. Покупки «для души», которые не видны другим (красивое нижнее белье, эзотерическая литература, предметы для алтаря/медитаций).",
          "Удовольствия: Уединенный отдых на природе, у моря, ретриты, спа-процедуры в закрытых клиниках, медитации, наслаждение тишиной и сном.",
          "Личная жизнь: Тайные романы, глубокая душевная связь на расстоянии, исцеление от прошлых любовных травм с помощью психолога."
        ]
      }
    }
  },
  "Mars": {
    "meta": {
      "lead": "Лучшее время для проявления активности, инициативности и старта проектов в темах"
    },
    "houses": {
      "1": {
        "theme": "Личность, тело, физические силы, имидж. Марс дает колоссальный заряд личной энергии",
        "items": [
          "Идеальное время для запуска личного стартапа, блога или проекта, где вы будете выступать «лицом» и лидером. Действуйте смело!",
          "Пик спортивных достижений. Начинайте новые интенсивные тренировки, ставьте личные рекорды, записывайтесь на марафоны"
        ]
      },
      "2": {
        "theme": "Финансы, ресурсы, инструменты заработка. Фокус на материализации усилий и монетизации",
        "items": [
          "Проявляйте инициативу в любых финансовых вопросах. Запуск и вложения средств в личные проекты, направленные на быстрый заработок, монетизацию хобби или создание нового потока доходов",
          "Покупка абонемента в зал, оплата услуг персонального тренера. Инвестиция времени в тело = инвестиция в ресурс",
          "Отличное время для покупки рабочих инструментов, оборудования, которое поможет зарабатывать (ноутбук, профессиональная техника)"
        ]
      },
      "3": {
        "theme": "Коммуникации, короткие поездки, документы. Пик логистической активности",
        "items": [
          "Запуск курсов, онлайн-школ, блогов, служб доставки, издательских проектов. Инициатива в учёбе и коммуникации",
          "Активные поездки (велосипед вместо метро), бег на короткие дистанции, единоборства (отработка скорости реакции)",
          "Идеальное время для покупки автомобиля, а также мотоциклов, велосипедов, самокатов, смартфонов, ноутбуков"
        ]
      },
      "4": {
        "theme": "Недвижимость, дом, семья, дача, переезд",
        "items": [
          "Запуск домашнего бизнеса, старта в сфере недвижимости, ремонтных работ, сельского хозяйства. Хорошее время для ремонта или переезда",
          "Тяжелая физическая работа по дому, копание в саду, обустройство домашней спортзоны",
          "Отличное время для покупки крупной бытовой техники (холодильник, стиральная машина, мебель), а также покупки автомобиля для семьи или обустройства гаража"
        ]
      },
      "5": {
        "theme": "Творчество, дети, спорт, развлечения, риски",
        "items": [
          "Запуск любых новых проектов, особенно творческих, развлекательных, ивент-проектов, открытие спортивных секций для детей",
          "Командные виды спорта, танцы, экстремальные развлечения, активные игры с детьми",
          "Высокий риск импульсивных трат и азартных игр — контролируйте бюджет!"
        ]
      },
      "6": {
        "theme": "Рутина, здоровье, работа, сервис. Пик эффективности и служения",
        "items": [
          "Оптимизация бизнес-процессов, запуск сервисных служб, внедрение новых алгоритмов работы",
          "Ежедневные дисциплинированные тренировки, ЛФК, йога, работа с осанкой, чёткий режим",
          "Хорошее время для плановых операций, стоматологии, лазерных коррекций, косметологических инъекций"
        ]
      },
      "7": {
        "theme": "Партнерства, брак, контракты. Фокус на совместных действиях и юридических вопросах",
        "items": [
          "Запуск совместного бизнеса, подписание важных контрактов, старт переговоров",
          "Парные тренировки, теннис, фехтование, спарринги, танцы с партнером",
          "Время страсти в отношениях, не упустите это время!"
        ]
      },
      "8": {
        "theme": "Кризисы, чужие деньги, хирургия и трансформация. Зона максимального напряжения и высвобождения энергии",
        "items": [
          "Антикризисный менеджмент, запуск проектов в сфере налогов, аудита, психологии, эзотерики",
          "Травмоопасный период, будьте осторожны. Сбрасывайте энергию через иглоукалывание/гвоздестояние/применение пиявок, глубокую проработку психосоматики через тело",
          "Покупка техники в кредит, оформление страховок на авто и здоровье"
        ]
      },
      "9": {
        "theme": "Дальние поездки, иностранные культуры, право, крупный транспорт. Фокус на расширении границ и глобальных движениях",
        "items": [
          "Запуск образовательных проектов, издательств, онлайн-школ и обучений, юридических консультаций. Инициативы в иностранной сфере",
          "Походы в горы, альпинизм, длинные велосипедные прогулки, спортивные ретриты за границей"
        ]
      },
      "10": {
        "theme": "Карьера, статус, общество, официальный транспорт. Пик социальной и профессиональной активности",
        "items": [
          "Активно прокладывайте путь на новый карьерный уровень, удовлетворяйте свои амбиции. Запуск масштабной компании, политические или общественные инициативы",
          "Профессиональный спорт, публичные челленджи, найм элитного тренера",
          "Хорошее время для покупки статусного авто (представительского класса), дорогой офисной техники, крупного оборудования для повышения профессионального статуса"
        ]
      },
      "11": {
        "theme": "Соцсети, технологии, будущее, авиация и инновации. Фокус на коллективных целях и высоких технологиях",
        "items": [
          "Запуск интернет-проектов, блоггинг, IT-стартапов, сетевых проектов, экологических или социальных движений",
          "Любые групповые или командные тренировки, использование фитнес-трекеров и приложений поможет держать ритм тренировок",
          "Хорошее время для покупки инновационной техники: электромобили, дроны, умный дом. Покупка через краудфандинг"
        ]
      },
      "12": {
        "theme": "Уединение, подсознание, скрытые процессы. Время скрытых действий, лечения и работы «в тени»",
        "items": [
          "Научные исследования, написание книги в уединении, благотворительные проекты, теневой PR. Время заходить в глубокие личные трансформации через тренинги, практики, психологию",
          "Плавание, реабилитация, медитативные практики, ходьба в одиночестве на природе",
          "Не время покупать авто — высок риск скрытых дефектов, «утопленников» или проблем, которые всплывут позже"
        ]
      }
    }
  },
  "Jupiter": {
    "meta": {
      "lead": "Лучшее время для повышения авторитета, расширения, увеличения и привнесения чего-то нового в темах"
    },
    "houses": {
      "1": {
        "theme": "Период выхода из тени, расширения влияния своей личности",
        "items": [
          "Запускайте личный бренд, становитесь публичной фигурой, начинайте вести блог. Время выйти из тени, заявить о себе и расширить влияние своей личности",
          "Работайте над уверенностью в себе, учитесь выступать на публике",
          "Риск набора веса (следите за питанием), но также это время для расширения физических возможностей (включайтесь в активный спорт)"
        ]
      },
      "2": {
        "theme": "Период наращивания материального благополучия и ресурсов",
        "items": [
          "Ищите новые, дополнительные источники дохода. Повышайте чек на свои услуги, выходите на рынок с более дорогим продуктом",
          "Увеличивайте накопления. Покупка недвижимости, земли, инвестиции",
          "Возможно учащение простудных и аллергических заболеваний. Важно работать на опережение и заниматься укреплением своего здоровья"
        ]
      },
      "3": {
        "theme": "Период расширения своих знаний, круга общения, аудитории и интеллектуального влияния",
        "items": [
          "Запуск масштабных медиа-проектов, написание книги, создание онлайн-курса. Ваш голос сейчас слышен далеко",
          "Поступайте в магистратуру, получайте престижные сертификаты, изучайте иностранные языки",
          "Выступайте на конференциях, проводите вебинары, расширяйте сеть контактов (нетворкинг), больше путешествуйте",
          "Риск появления проблем с оформлением документов"
        ]
      },
      "4": {
        "theme": "Период улучшения условий жизни и расширения семьи",
        "items": [
          "Переезжайте в новое, улучшенное жильё, покупайте загородную недвижимость, глобальный ремонт с расширением площади",
          "Улучшайте отношения с семьёй, оказывайте финансовую поддержку родственникам, создание семейных традиций и бизнесов",
          "Создавайте домашний офис или пространство для приема важных гостей",
          "Риск конфликтов с родителями, тяжёлой домашней атмосферы"
        ]
      },
      "5": {
        "theme": "Период творческого взлета, создания и запуска своих проектов, время удовольствий, романтики и детей",
        "items": [
          "Масштабируйте и монетизируйте своё творчество, запускайте свои проекты, открывайте студию. Инвестируйте в то, что вам близко",
          "Уделяйте время удовольствиям, флирту и развитию привлекательности. Планируйте рождение детей, инвестируйте в их образование и развитие",
          "Риск потери бизнеса или разочарования в увлечениях"
        ]
      },
      "6": {
        "theme": "Период для расширения своего бизнеса через улучшение услуг, найм персонала, заботу о своём здоровье",
        "items": [
          "Нанимайте помощников, персонал для делегирования рабочей/домашней рутины. Забота о коллективе на работе",
          "Внедрение комплексных оздоровительных программ, профилактика здоровья, посещение врача/тренера",
          "Риск вынужденных визитов к врачам"
        ]
      },
      "7": {
        "theme": "Период роста через союзы, браки и официальные договорённости",
        "items": [
          "Создание совместных предприятий, привлечение щедрых инвесторов или бизнес-партнёров. Знакомства с потенциальным партнёром для брака",
          "Заводите важные связи, полезные контакты, общайтесь с наставниками, берите консультации у экспертов",
          "Риск конфликтов с партнёрами"
        ]
      },
      "8": {
        "theme": "Период для глубокого духовного роста, трансформации, расширения через чужие ресурсы",
        "items": [
          "Занимайтесь инвестициями в перспективные стартапы. Контактируйте с людьми из бизнес-среды, изучайте кризис-менеджмент",
          "Глубоко изучайте психологию, духовность, эзотерику. Занимайтесь духовными, энергетическими или психологическими практиками",
          "Риск травм, крупные энергетические или материальные потери"
        ]
      },
      "9": {
        "theme": "Период глобального роста, получения высшего образования",
        "items": [
          "Путешествуйте, общайтесь с иностранцами, живите в новой среде, изучайте другую культуру и философию, международный рынок",
          "Получайте дополнительное образование, учёную степень. Пишите и издавайте книги, создавайте образовательные продукты",
          "Риск разочарования в наставнике"
        ]
      },
      "10": {
        "theme": "Период для карьерного роста, повышения статуса",
        "items": [
          "Проявляйте активность в работе, стремитесь к повышению. Открывайте собственную компанию, запускайте масштабные проекты",
          "Повышайте свой статус и авторитет. Работайте над имиджем визионера и лидера. Выступайте перед большой аудиторией",
          "Обретайте покровителей, знакомьтесь с влиятельными людьми",
          "Риск ссор с руководством или влиятельными людьми, соперничества на работе"
        ]
      },
      "11": {
        "theme": "Период для масштабирования через соцсети, технологии и коллективные идеи",
        "items": [
          "Работайте над увеличением своей популярности, создавайте и раскручивайте свой блог, делайте вирусный контент",
          "Внедряйте инновации (ИИ, блокчейн) в свой бизнес",
          "Увеличивайте контакты, расширяйте круг общения, выступайте организатором крупных сообществ, масштабных фестивалей",
          "Исполняйте свои самые смелые мечты",
          "Риск хейта, риск пойти против общества/коллектива и испытать отвержение"
        ]
      },
      "12": {
        "theme": "Период уединения, внутреннего роста, мудрости и масштабных замыслов в тишине",
        "items": [
          "Занимайтесь глубокой духовной практикой, ретриты, наставничество, волонтёрство на высоком уровне. Будьте тайным благодетелем",
          "Занимайтесь написанием фундаментальных трудов в тайне, изучением тайных знаний, эзотерики, психологии",
          "Возможность получить скрытую поддержку от влиятельных людей",
          "Риск развития разного рода зависимостей"
        ]
      }
    }
  },
  "Saturn": {
    "meta": {
      "lead": "Лучшее время для определения зоны ответственности, обретения власти и статуса"
    },
    "houses": {
      "1": {
        "theme": "Время повзрослеть, взять жизнь в свои руки и стать автором своей судьбы",
        "items": [
          "Работайте над статусом независимой, самодостаточной и зрелой личности. Власть над собственными слабостями, импульсами и телом",
          "Тотальный контроль за своим здоровьем, внешним видом, распорядком дня и личными границами. Вы больше не можете перекладывать вину за свою жизнь на других",
          "Формирование жёсткой, но работающей рутины. Отказ от инфантильных привычек. Создание зрелого, непоколебимого имиджа, который вызывает уважение",
          "Риск депрессий, ощущения одиночества"
        ]
      },
      "2": {
        "theme": "Время контроля за личными финансами и ресурсами",
        "items": [
          "Работайте над статусом финансово независимого и состоятельного человека. Возьмите власть над своими желаниями и научитесь отличать истинные потребности от навязанных",
          "Полный аудит доходов и расходов. Ответственность за монетизацию своих талантов, уплату налогов и отказ от потребительских кредитов",
          "Создание «подушки безопасности», формирование пассивного дохода, инвестируйте в землю, недвижимость, строительство",
          "Риск потери денег или снижения уровня нормы, фоновая усталость, выгорание"
        ]
      },
      "3": {
        "theme": "Время ответственности в обучениях, документах, и коммуникации",
        "items": [
          "Работайте над статусом эксперта, чьё мнение уважают. Развивайте умение убеждать фактами, а не эмоциями",
          "В оформлении документов, договоров, обучении. Берите ответственность за отношения с близким кругом людей, соседями и за каждое сказанное слово",
          "Получайте знания, дипломы, сертификаты. Систематизируйте базу знаний, наводите порядок в документах, укрепляйте связи, контакты",
          "Риск отмены планов, проблем в пути"
        ]
      },
      "4": {
        "theme": "Время заниматься семьёй, недвижимостью, корнями",
        "items": [
          "Проявляйте себя хозяином на своей территории. Укрепляйте семейные традиции, создавайте новые родовые сценарии",
          "За пожилых родителей, детей, содержание жилья, семейный бюджет и психологический климат в доме. Решение застарелых семейных проблем",
          "Покупка собственной недвижимости (часто в ипотеку). Начинайте стройку или ремонт жилья, облагораживайте свой земельный участок",
          "Риск потери жилья, вынужденных переездов"
        ]
      },
      "5": {
        "theme": "Время ограничить развлечения, всерьёз заняться своим делом, превратить хобби в профессию или стать наставником",
        "items": [
          "Зарабатывайте авторитет в сфере творчества, бизнеса или педагогики. Стремитесь к статусу мастера, наставника, автора",
          "В воспитании и образовании детей, за завершение начатых творческих проектов",
          "Дисциплина в своих проектах, своём бизнесе, творчестве (регулярность вместо действий «по настроению»). Ограничивайте себя в развлечениях, откажитесь от азартных игр. Заведите сатурнианское хобби (йога, коллекционирование, изучение истории, антиквариат, винтаж)",
          "Риск проблем в любовной сфере, необходимость покровительствовать партнёрам"
        ]
      },
      "6": {
        "theme": "Время стать незаменимым профессионалом, отладить рутину и следить за здоровьем",
        "items": [
          "Работайте на статус высококлассного специалиста, мастера своего дела, надёжного сотрудника или эффективного руководителя среднего звена",
          "За своё физическое здоровье, чёткий рабочий график, качество выполняемых услуг и здоровье подчинённых/своих домашних животных",
          "Выстраивайте качественный рабочий процесс, ответственно относитесь к вопросу здоровья. Стабильность — это отсутствие болезней и наличие надёжного места",
          "Риск ухудшения здоровья"
        ]
      },
      "7": {
        "theme": "Время создавать прочные союзы и научиться держать слово",
        "items": [
          "Работайте на статус надёжного партнёра, супруга или бизнес-союзника. Начинайте вести серьёзные консультации, показывайте себя как серьёзного эксперта, переговорщика, медиатора",
          "Берите ответственность за выбор своего окружения и партнёров. Регистрируйте официальный брак, привлекайте бизнес-партнёров, заключайте долгосрочные контракты",
          "Вступайте в брак, занимайтесь урегулированием судебных тяжб. Стабильность через верность данным обещаниям",
          "Риск охлаждения в отношениях, разрыва договоров"
        ]
      },
      "8": {
        "theme": "Время научиться управлять хаосом и чужими деньгами",
        "items": [
          "Работайте на статус антикризисного менеджера, инвестора или психолога-профи. Обретайте власть над своими страхами, кризисами, чужими ресурсами",
          "За совместные бюджеты, кредиты, ипотеки, налоги, алименты, наследство и глубинные психологические трансформации",
          "Досрочно погашайте долги, оформляйте страховки, инвестируйте в долгосрочные проекты и недвижимость. Стабильность через терапию с психологом и отказ от токсичных зависимостей",
          "Риск депрессии, потери жизненных смыслов"
        ]
      },
      "9": {
        "theme": "Время ставить глобальные цели, стратегию, стремиться к высшему знанию",
        "items": [
          "Работайте на статус учёного, профессора, гуру, издателя или международного эксперта. Обретайте власть над умами через фундаментальные знания и убеждения",
          "За свою репутацию, за начало международных проектов, за качество своего образования и соответствие своих действий своим же убеждениям",
          "Получайте учёную степень, создавайте долгосрочную стратегию развития на 10+ лет. Стабильность через чёткую жизненную философию, обретение духовного наставника",
          "Риск духовного кризиса"
        ]
      },
      "10": {
        "theme": "Карьера, социум, высшая власть. Пик социального триумфа и обретения высшей власти",
        "items": [
          "Работайте на достижение карьерных высот, признание обществом. Стремитесь к статусу человека, который «сделал себя сам»",
          "В повышении своей квалификации через курсы, увеличение рабочей нагрузки, ответственность за свою компанию",
          "Через занятие более высокой должности, формируйте своё наследие. Стабильность через безупречную социальную репутацию",
          "Риск потери текущего места работы"
        ]
      },
      "11": {
        "theme": "Время стать лидером мнений и архитектором будущего",
        "items": [
          "Работайте на статус лидера сообщества, инфлюенсера. Власть через влияние на массы, участие в волонтёрской деятельности или создание благотворительных проектов",
          "За свою команду, за выполнение обещаний перед подписчиками/друзьями, за реализацию долгосрочных планов и проектов",
          "Вступление в закрытые клубы по интересам, создание надёжной сети контактов (нетворкинг), участие в проектах, которые будут работать в будущем или на благо общества",
          "Риск недопонимания в коллективе, потери единомышленников"
        ]
      },
      "12": {
        "theme": "Время стать мудрецом, обуздать своих демонов и обрести внутренний стержень",
        "items": [
          "Обретайте власть над своим подсознанием. Статус тайного советника, духовного наставника или мудреца",
          "За свои скрытые мотивы, психическое и физическое здоровье, и помогать тем, кто не может за себя постоять",
          "Берите аскезы, прощайте обидчиков, работайте с психотерапевтом, избавляйтесь от зависимостей и вредных привычек, занимайтесь творчеством. Стабильность через внутренний покой, уединение и принятие своих теневых сторон",
          "Риск вынужденного одиночества, изоляция"
        ]
      }
    }
  },
  "Uranus": {
    "meta": {
      "lead": "Лучшее время для полной трансформации, вливания новых возможностей и мощностей быстрого развития в темах"
    },
    "houses": {
      "1": {
        "theme": "Личность ↔ Партнерства",
        "items": [
          "Трансформация баланса между вашими личными интересами и интересами партнёра или общества. Время выйти из зависимости и обрести подлинную автономность в отношениях.",
          "1 дом: Ваше тело, имидж, способ самопрезентации, личная свобода и независимость",
          "7 дом: Браки, деловые союзы, открытые враги, контракты, отношения с клиентами и все отношения «один на один»",
          "Кардинально меняйте имидж, экспериментируйте со внешностью. Сделайте то, что всегда боялись — татуировка, стрижка, новая профессия. Уран здесь требует аутентичности — перестаньте играть роль, которую от вас ждут",
          "Пересмотрите все свои союзы. Меняйте подход к отношениям: если отношения держат вас в клетке — Уран даст силы их разорвать или трансформировать. Если вы в созависимости — это время выйти из неё",
          "Знакомства с необычными, эксцентричными людьми, которые расширяют ваше сознание. Браки и партнёрства с иностранцами, людьми из IT-сферы, учёными или просто очень свободными личностями",
          "Внедряйте новые технологии в личный бренд, используйте соцсети и инновации для самопрезентации и в своей работе",
          "Власть через свободу: отрезок пути, где человек стремится стать тем, кто не зависит от чужого мнения, но при этом умеет создавать равноправные, современные союзы"
        ]
      },
      "2": {
        "theme": "Личные ресурсы ↔ Чужие ресурсы",
        "items": [
          "Трансформация отношения к деньгам, собственности и глубинным ценностям. Время перестроить финансовую систему.",
          "2 дом: Ваши деньги, материальные ценности, самооценка, источники дохода",
          "8 дом: Кредиты, инвестиции, наследство, налоги, страховки, совместные бюджеты, кризисы",
          "Отказ от устаревших способов заработка. Поиск новых, инновационных источников дохода (криптовалюты, NFT, IT-проекты, фриланс через международные платформы). Уран здесь требует отказа от финансовой зависимости",
          "Пересмотрите отношения с банками, инвесторами, налоговой, официально ведите деятельность. Если вы в долговой яме — Уран даст нестандартное решение для выхода",
          "Внезапные наследства, выигрыши, неожиданные инвестиции. Но Уран даёт не стабильность, а скачки — будьте готовы к резким изменениям",
          "Используйте блокчейн, алгоритмический трейдинг, краудфандинг. Инвестируйте в стартапы и высокие технологии",
          "Власть через инновации: отрезок пути, где человек стремится стать тем, кто понимает новые финансовые инструменты и умеет монетизировать будущее"
        ]
      },
      "3": {
        "theme": "Локальные знания ↔ Глобальные знания",
        "items": [
          "Трансформация интеллекта, коммуникаций и мировоззрения. Время выйти за пределы привычного круга общения и знаний.",
          "3 дом: Школьное образование, короткие поездки, братья/сёстры, соседи, локальные коммуникации, блогинг",
          "9 дом: Высшее образование, философия, религия, дальние путешествия, иностранные культуры, издательская деятельность",
          "Отказывайтесь от устаревших убеждений, догм, предрассудков. Уран здесь требует интеллектуальной свободы — изучайте то, что действительно зажигает, а не то, что «надо»",
          "Активно ведите соцсети, блог, учитесь и знакомьтесь онлайн. Изучайте иностранные языки, создавайте контент на нескольких языках. Разрывайте токсичные связи с соседями или родственниками, если они тянут вас вниз",
          "Неожиданные поездки за границу, знакомства с иностранцами, приглашения преподавать или выступать на международных площадках. Публикация книг или курсов, которые изменят мировоззрение людей",
          "Используйте ИИ для работы, обучения, создание онлайн-курсов, подкастов, YouTube-каналов. Изучайте нейронауки, футурологию, квантовую физику",
          "Власть через знания: отрезок пути, где человек стремится стать тем, кто видит будущее и умеет объяснять сложные вещи простым языком"
        ]
      },
      "4": {
        "theme": "Дом и корни ↔ Карьера и статус",
        "items": [
          "Трансформация фундамента жизни и социального положения. Время перестроить базу и шагнуть на ступень выше в своей реализации.",
          "4 дом: Недвижимость, семья, родители, внутренний мир, психологический фундамент, место жительства",
          "10 дом: Профессия, репутация, социальный лифт, начальство, государственные структуры, наследие",
          "Переезжайте в другой город/страну, если текущее место вас ограничивает. Заботьтесь о родственниках и их здоровье, разрывайте токсичные семейные сценарии, прорабатывайте детские травмы",
          "Повышайте квалификацию или полностью смените профессию, запускайте собственный бизнес в сфере технологий, науки или социальных изменений. Отказывайтесь от работы «ради стабильности», если она убивает вашу свободу",
          "Неожиданные предложения о работе, приглашения в стартапы, переезд в другой город ради карьеры. Покупка «умного дома», внедрение технологий в быт",
          "Используйте систему smart home, работайте из любой точки мира, создавайте компании с удалённой командой",
          "Власть через инновации: отрезок пути, где человек работает над масштабом своей личности, стремится к популярности. Станьте тем, кто разрушает старые системы и создаёт новые (инфлюенсер, реформатор, инноватор)"
        ]
      },
      "5": {
        "theme": "Творчество и дети ↔ Сообщества и будущее",
        "items": [
          "Трансформация самовыражения, романтики и социальных связей. Время выйти за привычные рамки в самовыражении и наконец отыскать «своих» людей.",
          "5 дом: Творчество, романтика, дети, развлечения, спекуляции, самовыражение",
          "11 дом: Друзья, соцсети, коллективные проекты, мечты, технологии, гуманитарные идеи",
          "Отказывайтесь от «правильного» искусства в пользу экспериментального, авангардного, цифрового. Использование ИИ для генерации искусства, создание NFT, VR-инсталляций. Уран здесь требует отказа от шаблонов",
          "Перестраивайте свою личную жизнь, позволяйте себе влюбляться, экспериментируйте, пробуйте новое в отношениях",
          "Знакомьтесь через соцсети, участвуйте в фестивалях, выступайте на конференциях на большую аудиторию. Создавайте сообщества единомышленников вокруг вашей идеи",
          "Используйте соцсети для виральности, создавайте онлайн-сообщества, краудфандинг творческих проектов. Инвестируйте в IT-стартапы, криптовалюты",
          "Власть через сообщество: отрезок пути, где человек стремится стать лидером мнений, организатором движений, тем, кто объединяет людей вокруг идей"
        ]
      },
      "6": {
        "theme": "Рутина и здоровье ↔ Подсознание и духовность",
        "items": [
          "Трансформация повседневности, работы и внутренней жизни. Время полностью обновить здоровье и открыть для себя совершенно новые уровни восприятия.",
          "6 дом: Работа, здоровье, повседневные обязанности, домашние животные, сервис",
          "12 дом: Уединение, медитации, психика, скрытые враги, карма, духовные практики",
          "Автоматизируйте работу, делегируйте, используйте ИИ и роботов для выполнения скучных задач. Уран здесь требует отказа от «работы ради работы»",
          "Изучайте биохакинг, используйте фитнес-трекеры, генетические тесты, персонализированную медицину. Отказ от устаревших методов лечения в пользу инновационных",
          "Неожиданные озарения, инсайты, прорывы в медитативных практиках. Работа в сфере медицины будущего, нейронаук, психотехнологий",
          "Используйте приложения для медитации, VR для терапии, нейростимуляторы для повышения продуктивности. Работайте в удалённом формате, фриланс",
          "Власть через технологии: отрезок пути, где человек стремится стать тем, кто использует науку и технологии для оптимизации жизни и расширения сознания"
        ]
      },
      "7": {
        "theme": "Личность ↔ Партнерства",
        "items": [
          "Трансформация баланса между вашими личными интересами и интересами партнёра или общества. Время выйти из зависимости и обрести подлинную автономность в отношениях.",
          "1 дом: Ваше тело, имидж, способ самопрезентации, личная свобода и независимость",
          "7 дом: Браки, деловые союзы, открытые враги, контракты, отношения с клиентами и все отношения «один на один»",
          "Кардинально меняйте имидж, экспериментируйте со внешностью. Сделайте то, что всегда боялись — татуировка, стрижка, новая профессия. Уран здесь требует аутентичности — перестаньте играть роль, которую от вас ждут",
          "Пересмотрите все свои союзы. Меняйте подход к отношениям: если отношения держат вас в клетке — Уран даст силы их разорвать или трансформировать. Если вы в созависимости — это время выйти из неё",
          "Знакомства с необычными, эксцентричными людьми, которые расширяют ваше сознание. Браки и партнёрства с иностранцами, людьми из IT-сферы, учёными или просто очень свободными личностями",
          "Внедряйте новые технологии в личный бренд, используйте соцсети и инновации для самопрезентации и в своей работе",
          "Власть через свободу: отрезок пути, где человек стремится стать тем, кто не зависит от чужого мнения, но при этом умеет создавать равноправные, современные союзы"
        ]
      },
      "8": {
        "theme": "Личные ресурсы ↔ Чужие ресурсы",
        "items": [
          "Трансформация отношения к деньгам, собственности и глубинным ценностям. Время перестроить финансовую систему.",
          "2 дом: Ваши деньги, материальные ценности, самооценка, источники дохода",
          "8 дом: Кредиты, инвестиции, наследство, налоги, страховки, совместные бюджеты, кризисы",
          "Отказ от устаревших способов заработка. Поиск новых, инновационных источников дохода (криптовалюты, NFT, IT-проекты, фриланс через международные платформы). Уран здесь требует отказа от финансовой зависимости",
          "Пересмотрите отношения с банками, инвесторами, налоговой, официально ведите деятельность. Если вы в долговой яме — Уран даст нестандартное решение для выхода",
          "Внезапные наследства, выигрыши, неожиданные инвестиции. Но Уран даёт не стабильность, а скачки — будьте готовы к резким изменениям",
          "Используйте блокчейн, алгоритмический трейдинг, краудфандинг. Инвестируйте в стартапы и высокие технологии",
          "Власть через инновации: отрезок пути, где человек стремится стать тем, кто понимает новые финансовые инструменты и умеет монетизировать будущее"
        ]
      },
      "9": {
        "theme": "Локальные знания ↔ Глобальные знания",
        "items": [
          "Трансформация интеллекта, коммуникаций и мировоззрения. Время выйти за пределы привычного круга общения и знаний.",
          "3 дом: Школьное образование, короткие поездки, братья/сёстры, соседи, локальные коммуникации, блогинг",
          "9 дом: Высшее образование, философия, религия, дальние путешествия, иностранные культуры, издательская деятельность",
          "Отказывайтесь от устаревших убеждений, догм, предрассудков. Уран здесь требует интеллектуальной свободы — изучайте то, что действительно зажигает, а не то, что «надо»",
          "Активно ведите соцсети, блог, учитесь и знакомьтесь онлайн. Изучайте иностранные языки, создавайте контент на нескольких языках. Разрывайте токсичные связи с соседями или родственниками, если они тянут вас вниз",
          "Неожиданные поездки за границу, знакомства с иностранцами, приглашения преподавать или выступать на международных площадках. Публикация книг или курсов, которые изменят мировоззрение людей",
          "Используйте ИИ для работы, обучения, создание онлайн-курсов, подкастов, YouTube-каналов. Изучайте нейронауки, футурологию, квантовую физику",
          "Власть через знания: отрезок пути, где человек стремится стать тем, кто видит будущее и умеет объяснять сложные вещи простым языком"
        ]
      },
      "10": {
        "theme": "Дом и корни ↔ Карьера и статус",
        "items": [
          "Трансформация фундамента жизни и социального положения. Время перестроить базу и шагнуть на ступень выше в своей реализации.",
          "4 дом: Недвижимость, семья, родители, внутренний мир, психологический фундамент, место жительства",
          "10 дом: Профессия, репутация, социальный лифт, начальство, государственные структуры, наследие",
          "Переезжайте в другой город/страну, если текущее место вас ограничивает. Заботьтесь о родственниках и их здоровье, разрывайте токсичные семейные сценарии, прорабатывайте детские травмы",
          "Повышайте квалификацию или полностью смените профессию, запускайте собственный бизнес в сфере технологий, науки или социальных изменений. Отказывайтесь от работы «ради стабильности», если она убивает вашу свободу",
          "Неожиданные предложения о работе, приглашения в стартапы, переезд в другой город ради карьеры. Покупка «умного дома», внедрение технологий в быт",
          "Используйте систему smart home, работайте из любой точки мира, создавайте компании с удалённой командой",
          "Власть через инновации: отрезок пути, где человек работает над масштабом своей личности, стремится к популярности. Станьте тем, кто разрушает старые системы и создаёт новые (инфлюенсер, реформатор, инноватор)"
        ]
      },
      "11": {
        "theme": "Творчество и дети ↔ Сообщества и будущее",
        "items": [
          "Трансформация самовыражения, романтики и социальных связей. Время выйти за привычные рамки в самовыражении и наконец отыскать «своих» людей.",
          "5 дом: Творчество, романтика, дети, развлечения, спекуляции, самовыражение",
          "11 дом: Друзья, соцсети, коллективные проекты, мечты, технологии, гуманитарные идеи",
          "Отказывайтесь от «правильного» искусства в пользу экспериментального, авангардного, цифрового. Использование ИИ для генерации искусства, создание NFT, VR-инсталляций. Уран здесь требует отказа от шаблонов",
          "Перестраивайте свою личную жизнь, позволяйте себе влюбляться, экспериментируйте, пробуйте новое в отношениях",
          "Знакомьтесь через соцсети, участвуйте в фестивалях, выступайте на конференциях на большую аудиторию. Создавайте сообщества единомышленников вокруг вашей идеи",
          "Используйте соцсети для виральности, создавайте онлайн-сообщества, краудфандинг творческих проектов. Инвестируйте в IT-стартапы, криптовалюты",
          "Власть через сообщество: отрезок пути, где человек стремится стать лидером мнений, организатором движений, тем, кто объединяет людей вокруг идей"
        ]
      },
      "12": {
        "theme": "Рутина и здоровье ↔ Подсознание и духовность",
        "items": [
          "Трансформация повседневности, работы и внутренней жизни. Время полностью обновить здоровье и открыть для себя совершенно новые уровни восприятия.",
          "6 дом: Работа, здоровье, повседневные обязанности, домашние животные, сервис",
          "12 дом: Уединение, медитации, психика, скрытые враги, карма, духовные практики",
          "Автоматизируйте работу, делегируйте, используйте ИИ и роботов для выполнения скучных задач. Уран здесь требует отказа от «работы ради работы»",
          "Изучайте биохакинг, используйте фитнес-трекеры, генетические тесты, персонализированную медицину. Отказ от устаревших методов лечения в пользу инновационных",
          "Неожиданные озарения, инсайты, прорывы в медитативных практиках. Работа в сфере медицины будущего, нейронаук, психотехнологий",
          "Используйте приложения для медитации, VR для терапии, нейростимуляторы для повышения продуктивности. Работайте в удалённом формате, фриланс",
          "Власть через технологии: отрезок пути, где человек стремится стать тем, кто использует науку и технологии для оптимизации жизни и расширения сознания"
        ]
      }
    }
  },
  "Neptune": {
    "meta": {
      "lead": "Лучшее время для того чтобы погрузиться в духовный, эзотерический мир, познать баланс и обрести мудрость в темах"
    },
    "houses": {
      "1": {
        "theme": "Личность ↔ Партнерства",
        "items": [
          "Трансформация границ между «Я» и «Мы». Время научиться любить по-настоящему — без условий и ожиданий.",
          "1 дом: Ваше тело, имидж, эго, личные границы, способ самоидентификации",
          "7 дом: Браки, союзы, открытые враги, проекции на других, контракты, отношения с клиентами и все отношения «один на один»",
          "Перестаньте цепляться за образ «кто я». Вашей психике нужна гибкость — позвольте себе быть разным, текучим, как вода. Займитесь практикой медитации, танцами, искусством. Познавайте себя",
          "Пересмотрите все отношения через призму безусловной любви. Если в партнёрстве есть обман, иллюзии или созависимость — период их обнажит. Это время научиться любить, не владея",
          "Встреча с «родственной душой», психологом, духовным наставником, целителем или творческой музой. Потянет изучить вопросы экологии, заботы о животных, заняться благотворительностью",
          "Развивайте артистизм, эмпатию, интуицию, способности чувствовать других без слов. Занятия актёрским мастерством, музыкой, поэзией, живописью",
          "Мудрость через сострадание: отрезок пути, где человек стремится стать тем, кто умеет прощать, понимать и принимать других такими, какие они есть"
        ]
      },
      "2": {
        "theme": "Личные ресурсы ↔ Чужие ресурсы",
        "items": [
          "Трансформация отношения к материальному и духовному богатству. Время познать истинную ценность вещей.",
          "2 дом: Деньги, материальные ценности, самооценка, таланты, источники дохода",
          "8 дом: Кредиты, инвестиции, наследство, кризисы, оккультизм, трансформация, интимность",
          "Учитесь отличать истинное богатство от иллюзорного. Откажитесь от накопительства ради накопительства. Зарабатывайте через творчество, вдохновение, служение, целительство, искусство",
          "Пересмотрите отношения с деньгами. Если вы в долгах или зависимы от чужих ресурсов — период покажет корень проблемы. Это время научиться доверять Вселенной и потоку изобилия",
          "Доход через духовные практики, искусство, музыку, фотографию, работу с водой, психологию, эзотерику — через помощь людям. Создавайте несколько источников дохода",
          "Изучайте таро, астрологию, хиромантию, энергетические практики (Рейки, цигун). Работайте с наследством рода, родовой кармой",
          "Мудрость через отрешённость: отрезок пути, где человек стремится тем, кто владеет материальным, но не привязан к нему. Щедрость, бескорыстие и умение делиться"
        ]
      },
      "3": {
        "theme": "Локальные знания ↔ Глобальные знания",
        "items": [
          "Трансформация способа познания мира. Время перейти от логики к интуиции и мистическому опыту.",
          "3 дом: Школьное образование, коммуникации, короткие поездки, братья/сёстры, повседневное мышление",
          "9 дом: Высшее образование, философия, религия, дальние путешествия, мировоззрение, издательская деятельность",
          "Размываются границы между рациональным и мистическим. Учитесь слушать внутренний голос, знаки Вселенной, синхронистичные события. Изучайте то, что нельзя измерить — душу, дух, любовь",
          "Совершайте паломничества, ретриты, поездки в сакральные места. Знакомьтесь с духовными учителями, монахами, гуру — они перевернут ваше сознание",
          "Изучайте или пишите поэтические, мистические или философские книги. Учитесь на психолога или религиоведа. Путешествуйте, изучайте иностранные языки через погружение в культуру",
          "Идите в практики ясновидения, работу со снами, астральные путешествия, изучайте суфизм, каббалу, веданту, буддизм. Медитации на расширение сознания",
          "Мудрость через веру: отрезок пути, где человек стремится тем, кто знает больше, чем может объяснить. Вдохновение, поэзия и способность передавать невыразимое"
        ]
      },
      "4": {
        "theme": "Дом и корни ↔ Карьера и статус",
        "items": [
          "Трансформация фундамента жизни и социальной реализации. Время выстроить прочную духовную опору внутри себя и найти своё настоящее призвание.",
          "4 дом: Недвижимость, семья, родители, внутренний мир, психологический фундамент, родина",
          "10 дом: Профессия, репутация, социальный лифт, призвание, общественное служение, наследие",
          "Превратите своё жилище в храм, место силы, тихую гавань. Период требует, чтобы дом стал пространством для души",
          "Пересмотрите свою профессию через призму миссии. Если работа не приносит смысла — этот период её обесценит. Это время выбрать путь, связанный с тайными знаниями, помощью или творчеством: целитель, учитель, художник, психолог, музыкант",
          "Успех при работе заграницей, с иностранцами или в сфере искусства, медицины, парфюмерии, психологии, духовных практик. Период хорош для глубокого изучения истории своей страны, своего Рода",
          "Превращение карьеры в искусство. Использование интуиции в бизнесе, создание атмосферы, а не просто продуктов",
          "Мудрость через служение: отрезок пути, где человек стремится стать тем, кто живёт не для себя, а для других, умение жертвовать, сострадание и способность исцелять души"
        ]
      },
      "5": {
        "theme": "Творчество и дети ↔ Сообщества и будущее",
        "items": [
          "Трансформация самовыражения и целей. Это время вести за собой людей, делиться творчеством и полностью отдаться вдохновению.",
          "5 дом: Хобби, романтика, дети, развлечения, самовыражение, спекуляции",
          "11 дом: Друзья, соцсети, популярность, коллективные проекты, мечты, гуманитарные идеи, технологии",
          "Нептун здесь — главный покровитель муз и вдохновения. Занимайтесь искусством ради искусства, а не ради результата. Пишите, пойте, танцуйте, рисуйте — позвольте творчеству течь через вас",
          "Объединяйтесь с единомышленниками, создавайте сообщества, которые несут свет, помогают другим, продвигают гуманистические идеи",
          "Время приятных развлечений, романов и флирта. Встреча с творческой музой, рождение проектов или детей. Участие в благотворительных, экологических, духовных движениях",
          "Используйте искусство для исцеления (арт-терапия, музыкотерапия). Создание фильмов, музыки, книг, которые трогают души. Работа с образами, символами, архетипами",
          "Мудрость через вдохновение: отрезок пути, где человек стремится тем, кто умеет мечтать и вдохновлять других на мечты, способность создавать миры через искусство и идеи"
        ]
      },
      "6": {
        "theme": "Рутина и здоровье ↔ Подсознание и духовность",
        "items": [
          "Трансформация повседневности и внутренней жизни. Время обрести душевное спокойствие, научиться исцелять себя и других.",
          "6 дом: Работа, здоровье, повседневные обязанности, домашние животные, сервис",
          "12 дом: Уединение, медитации, психика, скрытые враги, карма, духовные практики, больницы",
          "Превратите свою работу в служение. Нептун здесь даёт дар целительства — через медицину, психологию, энергетику, помощь животным, уход за больными",
          "Время глубокой духовной практики, ретритов, работы с подсознанием, анализа снов, кармического очищения",
          "Растворение давних тянущихся проблем. Пробуждение интереса к альтернативной медицине, травничеству, исцеление от психосоматических болезней через духовные практики",
          "Практикуйте растворение эго, работайте с тенью, медитируйте на пустоту, изучайте адвайту, дзен-буддизм, суфизм. Развитие яснознания, целительских способностей",
          "Мудрость через принятие: отрезок пути, где человек стремится стать тем, кто понял иллюзорность материального мира, через смирение, принятие и способность быть проводником Высшей воли"
        ]
      },
      "7": {
        "theme": "Личность ↔ Партнерства",
        "items": [
          "Трансформация границ между «Я» и «Мы». Время научиться любить по-настоящему — без условий и ожиданий.",
          "1 дом: Ваше тело, имидж, эго, личные границы, способ самоидентификации",
          "7 дом: Браки, союзы, открытые враги, проекции на других, контракты, отношения с клиентами и все отношения «один на один»",
          "Перестаньте цепляться за образ «кто я». Вашей психике нужна гибкость — позвольте себе быть разным, текучим, как вода. Займитесь практикой медитации, танцами, искусством. Познавайте себя",
          "Пересмотрите все отношения через призму безусловной любви. Если в партнёрстве есть обман, иллюзии или созависимость — период их обнажит. Это время научиться любить, не владея",
          "Встреча с «родственной душой», психологом, духовным наставником, целителем или творческой музой. Потянет изучить вопросы экологии, заботы о животных, заняться благотворительностью",
          "Развивайте артистизм, эмпатию, интуицию, способности чувствовать других без слов. Занятия актёрским мастерством, музыкой, поэзией, живописью",
          "Мудрость через сострадание: отрезок пути, где человек стремится стать тем, кто умеет прощать, понимать и принимать других такими, какие они есть"
        ]
      },
      "8": {
        "theme": "Личные ресурсы ↔ Чужие ресурсы",
        "items": [
          "Трансформация отношения к материальному и духовному богатству. Время познать истинную ценность вещей.",
          "2 дом: Деньги, материальные ценности, самооценка, таланты, источники дохода",
          "8 дом: Кредиты, инвестиции, наследство, кризисы, оккультизм, трансформация, интимность",
          "Учитесь отличать истинное богатство от иллюзорного. Откажитесь от накопительства ради накопительства. Зарабатывайте через творчество, вдохновение, служение, целительство, искусство",
          "Пересмотрите отношения с деньгами. Если вы в долгах или зависимы от чужих ресурсов — период покажет корень проблемы. Это время научиться доверять Вселенной и потоку изобилия",
          "Доход через духовные практики, искусство, музыку, фотографию, работу с водой, психологию, эзотерику — через помощь людям. Создавайте несколько источников дохода",
          "Изучайте таро, астрологию, хиромантию, энергетические практики (Рейки, цигун). Работайте с наследством рода, родовой кармой",
          "Мудрость через отрешённость: отрезок пути, где человек стремится тем, кто владеет материальным, но не привязан к нему. Щедрость, бескорыстие и умение делиться"
        ]
      },
      "9": {
        "theme": "Локальные знания ↔ Глобальные знания",
        "items": [
          "Трансформация способа познания мира. Время перейти от логики к интуиции и мистическому опыту.",
          "3 дом: Школьное образование, коммуникации, короткие поездки, братья/сёстры, повседневное мышление",
          "9 дом: Высшее образование, философия, религия, дальние путешествия, мировоззрение, издательская деятельность",
          "Размываются границы между рациональным и мистическим. Учитесь слушать внутренний голос, знаки Вселенной, синхронистичные события. Изучайте то, что нельзя измерить — душу, дух, любовь",
          "Совершайте паломничества, ретриты, поездки в сакральные места. Знакомьтесь с духовными учителями, монахами, гуру — они перевернут ваше сознание",
          "Изучайте или пишите поэтические, мистические или философские книги. Учитесь на психолога или религиоведа. Путешествуйте, изучайте иностранные языки через погружение в культуру",
          "Идите в практики ясновидения, работу со снами, астральные путешествия, изучайте суфизм, каббалу, веданту, буддизм. Медитации на расширение сознания",
          "Мудрость через веру: отрезок пути, где человек стремится тем, кто знает больше, чем может объяснить. Вдохновение, поэзия и способность передавать невыразимое"
        ]
      },
      "10": {
        "theme": "Дом и корни ↔ Карьера и статус",
        "items": [
          "Трансформация фундамента жизни и социальной реализации. Время выстроить прочную духовную опору внутри себя и найти своё настоящее призвание.",
          "4 дом: Недвижимость, семья, родители, внутренний мир, психологический фундамент, родина",
          "10 дом: Профессия, репутация, социальный лифт, призвание, общественное служение, наследие",
          "Превратите своё жилище в храм, место силы, тихую гавань. Период требует, чтобы дом стал пространством для души",
          "Пересмотрите свою профессию через призму миссии. Если работа не приносит смысла — этот период её обесценит. Это время выбрать путь, связанный с тайными знаниями, помощью или творчеством: целитель, учитель, художник, психолог, музыкант",
          "Успех при работе заграницей, с иностранцами или в сфере искусства, медицины, парфюмерии, психологии, духовных практик. Период хорош для глубокого изучения истории своей страны, своего Рода",
          "Превращение карьеры в искусство. Использование интуиции в бизнесе, создание атмосферы, а не просто продуктов",
          "Мудрость через служение: отрезок пути, где человек стремится стать тем, кто живёт не для себя, а для других, умение жертвовать, сострадание и способность исцелять души"
        ]
      },
      "11": {
        "theme": "Творчество и дети ↔ Сообщества и будущее",
        "items": [
          "Трансформация самовыражения и целей. Это время вести за собой людей, делиться творчеством и полностью отдаться вдохновению.",
          "5 дом: Хобби, романтика, дети, развлечения, самовыражение, спекуляции",
          "11 дом: Друзья, соцсети, популярность, коллективные проекты, мечты, гуманитарные идеи, технологии",
          "Нептун здесь — главный покровитель муз и вдохновения. Занимайтесь искусством ради искусства, а не ради результата. Пишите, пойте, танцуйте, рисуйте — позвольте творчеству течь через вас",
          "Объединяйтесь с единомышленниками, создавайте сообщества, которые несут свет, помогают другим, продвигают гуманистические идеи",
          "Время приятных развлечений, романов и флирта. Встреча с творческой музой, рождение проектов или детей. Участие в благотворительных, экологических, духовных движениях",
          "Используйте искусство для исцеления (арт-терапия, музыкотерапия). Создание фильмов, музыки, книг, которые трогают души. Работа с образами, символами, архетипами",
          "Мудрость через вдохновение: отрезок пути, где человек стремится тем, кто умеет мечтать и вдохновлять других на мечты, способность создавать миры через искусство и идеи"
        ]
      },
      "12": {
        "theme": "Рутина и здоровье ↔ Подсознание и духовность",
        "items": [
          "Трансформация повседневности и внутренней жизни. Время обрести душевное спокойствие, научиться исцелять себя и других.",
          "6 дом: Работа, здоровье, повседневные обязанности, домашние животные, сервис",
          "12 дом: Уединение, медитации, психика, скрытые враги, карма, духовные практики, больницы",
          "Превратите свою работу в служение. Нептун здесь даёт дар целительства — через медицину, психологию, энергетику, помощь животным, уход за больными",
          "Время глубокой духовной практики, ретритов, работы с подсознанием, анализа снов, кармического очищения",
          "Растворение давних тянущихся проблем. Пробуждение интереса к альтернативной медицине, травничеству, исцеление от психосоматических болезней через духовные практики",
          "Практикуйте растворение эго, работайте с тенью, медитируйте на пустоту, изучайте адвайту, дзен-буддизм, суфизм. Развитие яснознания, целительских способностей",
          "Мудрость через принятие: отрезок пути, где человек стремится стать тем, кто понял иллюзорность материального мира, через смирение, принятие и способность быть проводником Высшей воли"
        ]
      }
    }
  },
  "Pluto": {
    "meta": {
      "lead": "Лучшее время для осознанной трансформации, разрушения старого ради обретения силы и создание крутого нового в темах"
    },
    "houses": {
      "1": {
        "theme": "Личность ↔ Партнерства",
        "items": [
          "Трансформация баланса между «Я» и «Мы». Время перестать казаться кем-то и проявить истинного себя.",
          "1 дом: Ваше тело, имидж, способ самопрезентации, личная власть и способность влиять на других",
          "7 дом: Браки, деловые союзы, открытые враги, контракты, отношения с клиентами и все отношения «один на один»",
          "Этот период безжалостно сжигает все маски и социальные роли. Перестаньте притворяться тем, кем вы не являетесь. Примите свою тень — агрессию, властность, потребность в контроле. Только признав их, вы обретёте подлинную силу",
          "Все партнёрства проходят через проверку. Если отношения построены на манипуляциях или созависимости — они разрушатся. Не сопротивляйтесь. Из пепла родятся союзы, основанные на взаимной силе. Если отношения пройдут кризис — они станут неуязвимыми",
          "Перестаньте пытаться контролировать других. Период учит: истинная власть — это владение собой. Работайте с психотерапевтом над глубинными паттернами контроля и жертвенности",
          "Партнёры будут зеркалить ваши вытесненные качества. Вместо борьбы с ними — интегрируйте эти качества в себя. То, что вас бесит в других — это ваша непроявленная сила",
          "После кризиса вы станете человеком, которого невозможно сломать. Пройдёте психологическую перестройку себя и своей жизни и научитесь любить глубоко, не теряя себя"
        ]
      },
      "2": {
        "theme": "Ресурсы ↔ Глубинные трансформации",
        "items": [
          "Трансформация системы ценностей. Переплавка ресурсов, талантов и денег. Корректировка жизненных приоритетов.",
          "2 дом: Личные финансы, материальные ценности, таланты, самооценка, способ заработка",
          "8 дом: Чужие ресурсы, кризисы, сексуальность, психологическая близость, освобождение от изжившего",
          "Период транзита по 2-му дому может значительно увеличить ваш доход либо принести финансовые потери, но это не наказание — это освобождение. Отпустите привязанность к вещам и деньгам как к источнику безопасности",
          "Период транзита по 8-му дому заставляет вас встретиться со страхом потери контроля, себя, потери всего. Не избегайте этого опыта. Пройдите через него осознанно — и вы обретёте несокрушимую внутреннюю силу. Соблюдайте максимальную осторожность, это травмоопасный период",
          "Научитесь управлять большими потоками энергии (денег, власти, сексуальности) без разрушения. Это требует абсолютной честности с собой. Доход от большого потока или коллектива людей, товаров, информации, грамотных инвестиций",
          "Работайте с глубинными страхами, травмами, вытесненными желаниями. Психотерапия, тантра, работа с телом — всё, что помогает встретиться с тьмой и трансформировать её в свет",
          "После кризиса вы станете человеком, которого невозможно купить или запугать. Ваша новая сила — в способности владеть вещами, а не позволять им владеть вами"
        ]
      },
      "3": {
        "theme": "Коммуникация ↔ Мировоззрение",
        "items": [
          "Трансформация мышления через разрушение догм. Время обрести подлинную мудрость, пересмотрев всё, что считалось подлинным ранее.",
          "3 дом: Мышление, обучение, коммуникация, документы, ближний круг, способ восприятия информации",
          "9 дом: Философия, религия, высшее образование, дальние поездки, убеждения, идеология",
          "Период транзита по 3-му дому разрушает иллюзию, что «знать» = «понимать». Ваш привычный способ мыслить упрётся в тупик. Транзит по 9-му дому разрушает все догмы, идеологии, религиозные системы. Появится желание сменить веру или эмигрировать",
          "Ваше слово становится оружием трансформации. Но эта сила требует абсолютной честности — иначе она превратится в манипуляцию. Учитесь говорить так, чтобы ваши слова меняли реальность",
          "Не бойтесь сомневаться во всём, во что вы верили. Сомнение — не враг мудрости, а её начало. Работайте с психотерапевтом над глубинными убеждениями, которые ограничивают вас",
          "После кризиса вы станете человеком, чьё слово имеет вес, потому что оно рождено из глубины. Ваша новая сила — в способности видеть сквозь иллюзии, не теряя сострадания к тем, кто ещё в них живёт"
        ]
      },
      "4": {
        "theme": "Фундамент ↔ Социальный статус",
        "items": [
          "Трансформация жизненного фундамента через кризис авторитетов. Время активной перестройки дома и статуса.",
          "4 дом: Дом, семья, корни, недвижимость, внутренний мир, психологическая база, родовые программы",
          "10 дом: Карьера, репутация, общественное признание, высшая власть, миссия, социальная реализация",
          "Период, когда вам нужно встать во главе семьи, дома и заняться его перестройкой, сейчас от вас зависит атмосфера в семье. Период транзита по 4-му дому может принести переезды, разрывы с семьёй, раскрытие семейных тайн — это освобождение от родовых программ",
          "Период транзита по 10-му дому даёт повышение в карьере, славу, статус и власть либо разрушает иллюзии о карьере и репутации. Не сопротивляйтесь — это расчистка места для подлинной миссии. Меняйте профессию",
          "Перестаньте строить карьеру на амбициях. Период учит: истинная власть рождается из служения. Ваша новая сила — в способности вести людей через кризисы, потому что сами прошли через них",
          "Работайте с родовыми кармами, семейными сценариями, вытесненными эмоциями. Исцелите то, что передавалось поколениями. Обретите подлинный дом внутри себя",
          "После кризиса вы станете человеком, чья власть основана не на титуле, а на подлинной силе духа. Ваша новая сила — в способности быть лидером, который ведёт не через контроль, а через пример трансформации"
        ]
      },
      "5": {
        "theme": "Творчество ↔ Коллективное",
        "items": [
          "Трансформация самовыражения через кризис индивидуальности. Время активного участия в коллективной деятельности.",
          "5 дом: Творческое самовыражение, дети, романтика, риски, хобби, способность радоваться",
          "11 дом: Друзья, социальные сети, сообщества, мечты, будущее, коллективные проекты, нетворкинг",
          "Период транзита по 5-му дому разрушает иллюзию, что творчество — это способ получить признание. Появится новое увлечение и огромное желание создавать новое. Транзит столкнёт с периодами «пустоты», невозможности творить — это начало прорыва в подлинное самовыражение",
          "Период транзита по 11-му дому разрушает иллюзии о дружбе и принадлежности. Возможны разрывы с друзьями, разочарование в сообществах. Это расчистка места для настоящей дружбы и единства",
          "Период учит, что ваша сила в способности быть уникальным, не растворяясь в толпе. Большая вовлечённость в коллективные мероприятия. Занимайтесь политической, общественной, благотворительной деятельностью. Рост популярности и конкуренции",
          "Примите свою потребность в аплодисментах, зависть, страх быть невидимым. Станьте мастером, чьё творчество рождено из глубины, а не из потребности в признании",
          "После кризиса вы станете человеком, способным вести людей через трансформацию, не теряя своей индивидуальности. Ваша новая сила — в способности создавать сообщества, основанные на подлинной силе"
        ]
      },
      "6": {
        "theme": "Служение ↔ Трансценденция",
        "items": [
          "Трансформация здоровья, рабочих процессов и подсознательных установок через отказ от неработающих систем. Время заменить выгорание и хаос на осознанную дисциплину и прочную внутреннюю опору.",
          "6 дом: Работа, здоровье, рутина, сервис, повседневные обязанности, отношение к телу и эффективность",
          "12 дом: Подсознание, скрытые страхи, психологические блоки, потребность в уединении и духовные практики",
          "Период транзита по 6-му дому разрушает старые рабочие процессы и представления о здоровье. Возможны болезни, кризисы в работе, но также — обретение подлинного здоровья через осознанность и полную перестройку распорядка дня",
          "Период транзита по 12-му дому заставляет вас встретиться с глубинными страхами, кармическими программами, духовными иллюзиями. Важно уединяться — это время для прямой встречи с тьмой для её трансформации",
          "Перестать убегать от реальности в духовные фантазии. Изучайте эзотерику, биоэнергетику, тайные знания. Но помните: истинное просветление — не в побеге от реальности, а в полном присутствии в ней. Заземляйтесь через рутину",
          "Работайте с психотерапевтом, медитируйте, ведите дневник сновидений. Всё, что вы вытесняете, не признаёте, станет управлять вами. Признайте свою тень — и она станет вашей силой",
          "После кризиса вы станете человеком, способным быть в мире и одновременно отстраняться от него. Ваша новая сила — в способности превращать рутину в духовную практику, не теряя связи с реальностью. Вы станете мастером присутствия"
        ]
      },
      "7": {
        "theme": "Личность ↔ Партнерства",
        "items": [
          "Трансформация баланса между «Я» и «Мы». Время перестать казаться кем-то и проявить истинного себя.",
          "1 дом: Ваше тело, имидж, способ самопрезентации, личная власть и способность влиять на других",
          "7 дом: Браки, деловые союзы, открытые враги, контракты, отношения с клиентами и все отношения «один на один»",
          "Этот период безжалостно сжигает все маски и социальные роли. Перестаньте притворяться тем, кем вы не являетесь. Примите свою тень — агрессию, властность, потребность в контроле. Только признав их, вы обретёте подлинную силу",
          "Все партнёрства проходят через проверку. Если отношения построены на манипуляциях или созависимости — они разрушатся. Не сопротивляйтесь. Из пепла родятся союзы, основанные на взаимной силе. Если отношения пройдут кризис — они станут неуязвимыми",
          "Перестаньте пытаться контролировать других. Период учит: истинная власть — это владение собой. Работайте с психотерапевтом над глубинными паттернами контроля и жертвенности",
          "Партнёры будут зеркалить ваши вытесненные качества. Вместо борьбы с ними — интегрируйте эти качества в себя. То, что вас бесит в других — это ваша непроявленная сила",
          "После кризиса вы станете человеком, которого невозможно сломать. Пройдёте психологическую перестройку себя и своей жизни и научитесь любить глубоко, не теряя себя"
        ]
      },
      "8": {
        "theme": "Ресурсы ↔ Глубинные трансформации",
        "items": [
          "Трансформация системы ценностей. Переплавка ресурсов, талантов и денег. Корректировка жизненных приоритетов.",
          "2 дом: Личные финансы, материальные ценности, таланты, самооценка, способ заработка",
          "8 дом: Чужие ресурсы, кризисы, сексуальность, психологическая близость, освобождение от изжившего",
          "Период транзита по 2-му дому может значительно увеличить ваш доход либо принести финансовые потери, но это не наказание — это освобождение. Отпустите привязанность к вещам и деньгам как к источнику безопасности",
          "Период транзита по 8-му дому заставляет вас встретиться со страхом потери контроля, себя, потери всего. Не избегайте этого опыта. Пройдите через него осознанно — и вы обретёте несокрушимую внутреннюю силу. Соблюдайте максимальную осторожность, это травмоопасный период",
          "Научитесь управлять большими потоками энергии (денег, власти, сексуальности) без разрушения. Это требует абсолютной честности с собой. Доход от большого потока или коллектива людей, товаров, информации, грамотных инвестиций",
          "Работайте с глубинными страхами, травмами, вытесненными желаниями. Психотерапия, тантра, работа с телом — всё, что помогает встретиться с тьмой и трансформировать её в свет",
          "После кризиса вы станете человеком, которого невозможно купить или запугать. Ваша новая сила — в способности владеть вещами, а не позволять им владеть вами"
        ]
      },
      "9": {
        "theme": "Коммуникация ↔ Мировоззрение",
        "items": [
          "Трансформация мышления через разрушение догм. Время обрести подлинную мудрость, пересмотрев всё, что считалось подлинным ранее.",
          "3 дом: Мышление, обучение, коммуникация, документы, ближний круг, способ восприятия информации",
          "9 дом: Философия, религия, высшее образование, дальние поездки, убеждения, идеология",
          "Период транзита по 3-му дому разрушает иллюзию, что «знать» = «понимать». Ваш привычный способ мыслить упрётся в тупик. Транзит по 9-му дому разрушает все догмы, идеологии, религиозные системы. Появится желание сменить веру или эмигрировать",
          "Ваше слово становится оружием трансформации. Но эта сила требует абсолютной честности — иначе она превратится в манипуляцию. Учитесь говорить так, чтобы ваши слова меняли реальность",
          "Не бойтесь сомневаться во всём, во что вы верили. Сомнение — не враг мудрости, а её начало. Работайте с психотерапевтом над глубинными убеждениями, которые ограничивают вас",
          "После кризиса вы станете человеком, чьё слово имеет вес, потому что оно рождено из глубины. Ваша новая сила — в способности видеть сквозь иллюзии, не теряя сострадания к тем, кто ещё в них живёт"
        ]
      },
      "10": {
        "theme": "Фундамент ↔ Социальный статус",
        "items": [
          "Трансформация жизненного фундамента через кризис авторитетов. Время активной перестройки дома и статуса.",
          "4 дом: Дом, семья, корни, недвижимость, внутренний мир, психологическая база, родовые программы",
          "10 дом: Карьера, репутация, общественное признание, высшая власть, миссия, социальная реализация",
          "Период, когда вам нужно встать во главе семьи, дома и заняться его перестройкой, сейчас от вас зависит атмосфера в семье. Период транзита по 4-му дому может принести переезды, разрывы с семьёй, раскрытие семейных тайн — это освобождение от родовых программ",
          "Период транзита по 10-му дому даёт повышение в карьере, славу, статус и власть либо разрушает иллюзии о карьере и репутации. Не сопротивляйтесь — это расчистка места для подлинной миссии. Меняйте профессию",
          "Перестаньте строить карьеру на амбициях. Период учит: истинная власть рождается из служения. Ваша новая сила — в способности вести людей через кризисы, потому что сами прошли через них",
          "Работайте с родовыми кармами, семейными сценариями, вытесненными эмоциями. Исцелите то, что передавалось поколениями. Обретите подлинный дом внутри себя",
          "После кризиса вы станете человеком, чья власть основана не на титуле, а на подлинной силе духа. Ваша новая сила — в способности быть лидером, который ведёт не через контроль, а через пример трансформации"
        ]
      },
      "11": {
        "theme": "Творчество ↔ Коллективное",
        "items": [
          "Трансформация самовыражения через кризис индивидуальности. Время активного участия в коллективной деятельности.",
          "5 дом: Творческое самовыражение, дети, романтика, риски, хобби, способность радоваться",
          "11 дом: Друзья, социальные сети, сообщества, мечты, будущее, коллективные проекты, нетворкинг",
          "Период транзита по 5-му дому разрушает иллюзию, что творчество — это способ получить признание. Появится новое увлечение и огромное желание создавать новое. Транзит столкнёт с периодами «пустоты», невозможности творить — это начало прорыва в подлинное самовыражение",
          "Период транзита по 11-му дому разрушает иллюзии о дружбе и принадлежности. Возможны разрывы с друзьями, разочарование в сообществах. Это расчистка места для настоящей дружбы и единства",
          "Период учит, что ваша сила в способности быть уникальным, не растворяясь в толпе. Большая вовлечённость в коллективные мероприятия. Занимайтесь политической, общественной, благотворительной деятельностью. Рост популярности и конкуренции",
          "Примите свою потребность в аплодисментах, зависть, страх быть невидимым. Станьте мастером, чьё творчество рождено из глубины, а не из потребности в признании",
          "После кризиса вы станете человеком, способным вести людей через трансформацию, не теряя своей индивидуальности. Ваша новая сила — в способности создавать сообщества, основанные на подлинной силе"
        ]
      },
      "12": {
        "theme": "Служение ↔ Трансценденция",
        "items": [
          "Трансформация здоровья, рабочих процессов и подсознательных установок через отказ от неработающих систем. Время заменить выгорание и хаос на осознанную дисциплину и прочную внутреннюю опору.",
          "6 дом: Работа, здоровье, рутина, сервис, повседневные обязанности, отношение к телу и эффективность",
          "12 дом: Подсознание, скрытые страхи, психологические блоки, потребность в уединении и духовные практики",
          "Период транзита по 6-му дому разрушает старые рабочие процессы и представления о здоровье. Возможны болезни, кризисы в работе, но также — обретение подлинного здоровья через осознанность и полную перестройку распорядка дня",
          "Период транзита по 12-му дому заставляет вас встретиться с глубинными страхами, кармическими программами, духовными иллюзиями. Важно уединяться — это время для прямой встречи с тьмой для её трансформации",
          "Перестать убегать от реальности в духовные фантазии. Изучайте эзотерику, биоэнергетику, тайные знания. Но помните: истинное просветление — не в побеге от реальности, а в полном присутствии в ней. Заземляйтесь через рутину",
          "Работайте с психотерапевтом, медитируйте, ведите дневник сновидений. Всё, что вы вытесняете, не признаёте, станет управлять вами. Признайте свою тень — и она станет вашей силой",
          "После кризиса вы станете человеком, способным быть в мире и одновременно отстраняться от него. Ваша новая сила — в способности превращать рутину в духовную практику, не теряя связи с реальностью. Вы станете мастером присутствия"
        ]
      }
    }
  }
}